{"txid":"223a08cb9896109ff9c2bc2447318a919f0b5f6d9cf713d0e48bfe100a293c88","confirmations":14237,"time":1550927125,"is_coinbase":false,"is_double_spend":false,"is_sw_tx":true,"weight":5062,"vsize":1266,"inputs_count":1,"outputs_count":36,"inputs_value":906077096,"outputs_value":906033108,"max_prev_time":1550925867,"min_prev_time":1550925867,"avg_prev_time":1550925867,"max_prev_val":977355712,"min_prev_val":977355712,"avg_prev_val":977355712,"list_of_input":[{"prev_address":"35gWVCbsDqw9Ud9WpfVxk9tUeRFovRVkgH","curr_value":906077096,"prev_time":1550925867,"total_prev_val":977355712}],"max_next_time":1553316997,"min_next_time":1550928242,"avg_next_time":1551053225,"max_next_val":775892463,"min_next_val":1844238,"avg_next_val":124191848,"list_of_output":[{"next_address":"3EeUszpZ6WP1joZH9XR8eY7vgXs4XpbGwi","curr_value":548960,"next_time":1550934034,"total_next_val":1844238},{"next_address":"18CVogRnEjTNgqcbFWH5Gw4MsF9kqUGsrt","curr_value":5258158,"next_time":1550929159,"total_next_val":5258158},{"next_address":"3M27hx3DUvhtSx1dWZpBhLViuh5wPQKXhs","curr_value":723200,"next_time":1550930798,"total_next_val":120720768},{"next_address":"1JfquTHVyN1TF8f4yjYDNjuLaxPCdipKVT","curr_value":1167000,"next_time":1553316997,"total_next_val":98606085},{"next_address":"3NBjQmnxLvZ2NcL8JqtoFEAMj6g8emU2JL","curr_value":357345,"next_time":1550973416,"total_next_val":108766862},{"next_address":"3DYJcCqzZvLt6FDbvPJLRc494JhrRKDeUi","curr_value":942180,"next_time":1550928682,"total_next_val":69767982},{"next_address":"3D1VsCCsZCAuN8VfcuaZWkTKopRJ99eHVT","curr_value":704088,"next_time":1550938552,"total_next_val":16140232},{"next_address":"1LUHayiQgPxeYRP9JzbcDLtAWEXenJWhjk","curr_value":899100,"next_time":1550932449,"total_next_val":76492781},{"next_address":"3BQLxVLjXF4SbWkWE4pqvS6HhzEKgKbyFD","curr_value":889488,"next_time":1550928682,"total_next_val":69767982},{"next_address":"345MVveyxNuYbmB7Ppx4zxb2WbxJvYe3iA","curr_value":543901,"next_time":1551083151,"total_next_val":45853881},{"next_address":"38rpPYsJV7kv8dJDftDhBicUAPay8osmHu","curr_value":1041181,"next_time":1550928682,"total_next_val":69767982},{"next_address":"3PrxyFEaJKwdY7yRdmxrgBVbQF9Wjs8rBN","curr_value":37347,"next_time":1550929159,"total_next_val":119846289},{"next_address":"3Lguwxgd2ESDAgs9SUdWsWvZ8S1Q4tyXMt","curr_value":1531430,"next_time":1551041434,"total_next_val":106485603},{"next_address":"3AU2effsWbP4N79GU9pB651xkBJfm53fNc","curr_value":16755,"next_time":1550929159,"total_next_val":119846289},{"next_address":"3HGpm4NtLzosy6PbH1EvoyTggAxwiTe6k3","curr_value":450208,"next_time":1550973318,"total_next_val":111037042},{"next_address":"34JnyXkyega1Drt3R791PPncMiyZTCsF22","curr_value":647649,"next_time":1550937613,"total_next_val":48279984},{"next_address":"3E4czphE148E23JGovgPUwKUy5gVtgByN6","curr_value":4002292,"next_time":1551062639,"total_next_val":544643327},{"next_address":"1P7Rafcvh5PmtqY9gSmbMSbT1npatbCmbz","curr_value":10000,"next_time":1551098703,"total_next_val":1893372},{"next_address":"32qqXJVdpTuG4sv72zgxawQaXdPQmNJnQN","curr_value":1251359,"next_time":1550977065,"total_next_val":10815080},{"next_address":"3AwwA7SGkkEP6DwWJyMCe4sHJRVNcebgUh","curr_value":357980,"next_time":1551080038,"total_next_val":123887601},{"next_address":"37aMT72smZngBzmVaYpgeMUbqW9QXhbm35","curr_value":480000,"next_time":1551099660,"total_next_val":222104365},{"next_address":"3N9qVmjbpwU1PMzPG3pDHDGPNR3Bwmjg28","curr_value":442845,"next_time":1551005061,"total_next_val":126962273},{"next_address":"3JvxSbDZ1fbaBg9X4DctKxeRYxU3zq2eCv","curr_value":730000,"next_time":1550929159,"total_next_val":171724714},{"next_address":"1Dhf36ECvxscwxC7JuN6BULwfpJ43FoRYB","curr_value":98190000,"next_time":1551103101,"total_next_val":102925303},{"next_address":"3H2vYpYin5YajtaBc2TfQytZyvSV1nvCn7","curr_value":316954,"next_time":1550942070,"total_next_val":124441925},{"next_address":"3EkS418nbWmQmfZdM7AwvKHkxuH254ZENW","curr_value":1783213,"next_time":1550929180,"total_next_val":111421324},{"next_address":"3B7vpyZMYSpXsR133zPjdYdvhyG93Y3pWN","curr_value":200000,"next_time":1550997759,"total_next_val":201278968},{"next_address":"3GHNyHEosAHMnighmc28XiMFw8XJyM2Xgs","curr_value":692373,"next_time":1550948062,"total_next_val":192396738},{"next_address":"3KQAoezK3cVmmFjbU3Dq8YYsfrpubXQ1d4","curr_value":815902,"next_time":1550930684,"total_next_val":5851213},{"next_address":"37XKZgkrkNetYUp7gs2J3wnrbfUEFWbLYU","curr_value":575775,"next_time":1550965517,"total_next_val":141777346},{"next_address":"1CuJVbRFpeLHcC32jYdf4UhDs3sVnULy1e","curr_value":518483,"next_time":1551516999,"total_next_val":14026956},{"next_address":"3A1kfEhC5Wspqxg9AGwTT1goy9byRs2JtF","curr_value":1737080,"next_time":1550929159,"total_next_val":116955017},{"next_address":"3Ja2H8Ye4WyGA3XceZEjaRgjVj7v6X2ugA","curr_value":630375,"next_time":1550979867,"total_next_val":112237091},{"next_address":"3EfQobZ6VFzix6khd5fzPFXE85kR3w1J6k","curr_value":927871,"next_time":1550928682,"total_next_val":69767982},{"next_address":"3NCpdfwHomBn5jxSYqWRCgzXVST68hmyNY","curr_value":775892463,"next_time":1550928242,"total_next_val":775892463},{"next_address":"32nmoK8DN2ewGbRkPFYLmr5JARoEWHoxeX","curr_value":720153,"next_time":1550929180,"total_next_val":111421324}],"diff_max_prev_time":1258,"diff_min_prev_time":1258,"diff_avg_prev_time":1258,"diff_max_next_time":2389872,"diff_min_next_time":1117,"diff_avg_next_time":126100}