{"txid":"8ad649ae43b0bb0572b71e4aef6b44a62df5c85beaea35713dc37dd7e33cdaf6","confirmations":585,"time":1558913615,"is_coinbase":false,"is_double_spend":false,"is_sw_tx":true,"weight":1454,"vsize":364,"inputs_count":1,"outputs_count":8,"inputs_value":63320607,"outputs_value":63268866,"max_prev_time":1558913287,"min_prev_time":1558913287,"avg_prev_time":1558913287,"max_prev_val":196757049,"min_prev_val":196757049,"avg_prev_val":196757049,"list_of_input":[{"prev_address":"31pr5v9CiEZsPkAWerKiZz9PJcAwXdr9wR","curr_value":63320607,"prev_time":1558913287,"total_prev_val":196757049}],"max_next_time":1559038371,"min_next_time":1558913801,"avg_next_time":1558947372,"max_next_val":83796517,"min_next_val":148925,"avg_next_val":27553158,"list_of_output":[{"next_address":"3Q5hDnNBB87STRhMtTSw3jt3B6EM1vvitJ","curr_value":56323079,"next_time":1558913801,"total_next_val":56323079},{"next_address":"37nfbebY74pGgaJZUqDPiFj5foUhHtyS4q","curr_value":148925,"next_time":1558915649,"total_next_val":148925},{"next_address":"34XLFo6NrzzUzc6S6tDVD1kszHFnb3ZcvL","curr_value":300824,"next_time":1559038371,"total_next_val":83796517},{"next_address":"12ZwaVdTk7RTmpEgees4MrxaCFDmK8mEP7","curr_value":3680000,"next_time":1558970233,"total_next_val":3989067},{"next_address":"33uxyuNYPSfSmcL5zmrgn4tgaz3xMnYkDh","curr_value":142895,"next_time":1558934595,"total_next_val":44816128},{"next_address":"1KLbnz9aHvdVsdWXaTQ84rkeCWvjH663rZ","curr_value":2400000,"next_time":1558942336,"total_next_val":2400000},{"next_address":"3Ji7kBhS3hLQe7LufD4MbNombUFgkhMN7C","curr_value":200160,"next_time":1558916622,"total_next_val":1398389}],"diff_max_prev_time":328,"diff_min_prev_time":328,"diff_avg_prev_time":328,"diff_max_next_time":124756,"diff_min_next_time":186,"diff_avg_next_time":33757}