{"txid":"aedcb94357b25b4e23330ac4d6b985b236f221efd4048b879ca31ca7d262c920","confirmations":22615,"time":1546185645,"is_coinbase":false,"is_double_spend":false,"is_sw_tx":true,"weight":36530,"vsize":9133,"inputs_count":100,"outputs_count":1,"inputs_value":152761331,"outputs_value":152752186,"max_prev_time":1546184226,"min_prev_time":1545902753,"avg_prev_time":1546137343,"max_prev_val":8116638131,"min_prev_val":1083695,"avg_prev_val":1418096207,"list_of_input":[{"prev_address":"3BZWLi3SucSwL2araTJf1FpGGb6pfu2QgF","curr_value":1917689,"prev_time":1546172918,"total_prev_val":536860864},{"prev_address":"35AaPdxqKLxdP9U4Z7A3jwyP7PBiHm8iyt","curr_value":2069768,"prev_time":1546118642,"total_prev_val":1249107561},{"prev_address":"3EUpRJcgry5M7FApSQmMKobeV4sYVftgJt","curr_value":468401,"prev_time":1546130113,"total_prev_val":14882612},{"prev_address":"3KKp8V6ZeZ6d3PmtMvKcpHEpscVzceggUS","curr_value":2498800,"prev_time":1546085114,"total_prev_val":3090641},{"prev_address":"3L2ma5WN4rsB8i9S8UoYAuZ1U4RvXbBYDM","curr_value":407374,"prev_time":1546167385,"total_prev_val":3281159291},{"prev_address":"3JviWp9yZjnoMzDrb3jEGi9UYgJBvRCFYA","curr_value":1172500,"prev_time":1545974381,"total_prev_val":1176200},{"prev_address":"328ff3jF98qMjD1yyr3r6zQBQjTWnFqFB9","curr_value":1282637,"prev_time":1546182093,"total_prev_val":1307345158},{"prev_address":"3A6XaYViL9GvDSM6kqVhi5YEby1VUrVg2D","curr_value":1440590,"prev_time":1546092139,"total_prev_val":733430257},{"prev_address":"38qauQz2k5t59CaUcCEoMBznTdAnh56xBg","curr_value":2362200,"prev_time":1546168619,"total_prev_val":55321128},{"prev_address":"32mPnwMhseGoMeZayg8vZPndNp22knxtGK","curr_value":402224,"prev_time":1546074733,"total_prev_val":2593855035},{"prev_address":"34pqXRFjg5zHqgiukNzSoBYE4yyLXXJcPL","curr_value":693080,"prev_time":1546180824,"total_prev_val":2318844867},{"prev_address":"3LWTGrxuyxgqn7pD5UgtfznBseyT26JzfL","curr_value":1158636,"prev_time":1546155323,"total_prev_val":1309711177},{"prev_address":"3LZTSZQvfReWvasYGGms1di8iY4bW6Y1Qo","curr_value":658183,"prev_time":1546179020,"total_prev_val":1278269143},{"prev_address":"3FfqfTLYE7VHFRg24aQPLVLNMGScoZCkQb","curr_value":1587345,"prev_time":1546178864,"total_prev_val":6474615779},{"prev_address":"3HAmEDQTuzPtskZUNTF7t9TiD9S3ftaTwZ","curr_value":1407210,"prev_time":1546013936,"total_prev_val":2408043},{"prev_address":"3Bk8VvYKbrrjUjvnM9oV8iMQ41Gyu4LFo9","curr_value":530198,"prev_time":1546169131,"total_prev_val":1060063768},{"prev_address":"34uDVgEVQduq86pKSSvzgT948iE2peA4L3","curr_value":1227828,"prev_time":1546054433,"total_prev_val":2782546146},{"prev_address":"34uhKhYZwpPiExhETHkkAWXRWCtms79ERB","curr_value":1865000,"prev_time":1546169131,"total_prev_val":2811645410},{"prev_address":"3CWy3GDoCStBwtU4jP5Me4Y65s4FYoRxFT","curr_value":2100000,"prev_time":1546118390,"total_prev_val":2300272},{"prev_address":"3B5bLKLBNhZTEeHKuAC7PtjfKvFfb7NSpa","curr_value":716300,"prev_time":1546184226,"total_prev_val":267691937},{"prev_address":"3CLf8Z3AuRHNmXpQ47n1VBJ2cUtNJZC6iz","curr_value":1630000,"prev_time":1546091349,"total_prev_val":1012412469},{"prev_address":"3HAswmh1dpsGZx9YF48dtxB3igPPgBdHBm","curr_value":3200000,"prev_time":1546110937,"total_prev_val":5927644574},{"prev_address":"3B5GKP8y5TmHXeAvZ2cgfqvyrS1KMCMe2r","curr_value":2620790,"prev_time":1546177804,"total_prev_val":179864891},{"prev_address":"31hT7ATZfpsxbmcgs4kzxUnc4B9vndoko6","curr_value":549020,"prev_time":1546179553,"total_prev_val":248820456},{"prev_address":"3CB94mRWrg1ASxmWoeDc69ESPCi1Qz62z2","curr_value":1375670,"prev_time":1545902753,"total_prev_val":54063214},{"prev_address":"39NT4TP5oaQmG5fhW2abAXAXMb3GtDzyb8","curr_value":403719,"prev_time":1546169712,"total_prev_val":57824974},{"prev_address":"3FBS8ZCmBvhKW3scDeXG4gxhmw1KkAB8wN","curr_value":2620000,"prev_time":1546184226,"total_prev_val":37793101},{"prev_address":"3BmUfBH9hZorjXYmQGgAnVe5k8kW5wQzkV","curr_value":521884,"prev_time":1546184226,"total_prev_val":14832616},{"prev_address":"3Q1oKkSwnLcm2p8NX4yDR9LvvojBCuoenp","curr_value":1846664,"prev_time":1546050697,"total_prev_val":1895418407},{"prev_address":"33sTBdz75Me48xxCZXVZ7GNnewPLWMpweK","curr_value":427016,"prev_time":1546167385,"total_prev_val":2271974329},{"prev_address":"3KsDzntTQKoeGFuPfCTZaDJpRqpti4pTsf","curr_value":2800000,"prev_time":1546167385,"total_prev_val":1714976817},{"prev_address":"35PNwiYCeGFkJEMnpXwxfYiSC1WKmw61GJ","curr_value":2053546,"prev_time":1546180824,"total_prev_val":39951882},{"prev_address":"3G49NbmrPBHzwyH1tWHkD6ksopip65oNGq","curr_value":1667170,"prev_time":1546170148,"total_prev_val":5715624},{"prev_address":"39pPHBoNPyosLDqmZpqidSWFgmqDsUr6pY","curr_value":3311339,"prev_time":1546174370,"total_prev_val":1447953676},{"prev_address":"3ACF1jHpMhsjxnnNt5L8gXTrJDgSyD1uoF","curr_value":665162,"prev_time":1546184226,"total_prev_val":267691937},{"prev_address":"31rJ7pCdTY5ffcWxqRSDxnCTAWHG6RQp48","curr_value":1335895,"prev_time":1546096389,"total_prev_val":1270533533},{"prev_address":"3GNNbywVHd6jasnPaLB7cH9e9MqRAFnLKx","curr_value":1109206,"prev_time":1546184226,"total_prev_val":267691937},{"prev_address":"32uo7yG4jC2U7gCvnjzJZE4DSHvAUZFMbe","curr_value":634000,"prev_time":1546184226,"total_prev_val":1083695},{"prev_address":"38X9t2uJzHqUk3kdH1wBpsV3XSxaAq2Muy","curr_value":1705569,"prev_time":1546177804,"total_prev_val":157635659},{"prev_address":"3JvSX8ubfGhGfLgC96nafkWJP1AsWgdoQo","curr_value":1903327,"prev_time":1546012174,"total_prev_val":55918086},{"prev_address":"32jdoFHNmz4QkucoA6CBVKAV6U7dZkyrn8","curr_value":1167043,"prev_time":1546169712,"total_prev_val":2211061771},{"prev_address":"3N9q6APCk9baL6kzDSsFfdL7etwre2N84c","curr_value":1864000,"prev_time":1546112915,"total_prev_val":1184793788},{"prev_address":"3QNEoEZ4XzapC9DtvkitC4Rczz7eGrrSGy","curr_value":2303321,"prev_time":1546076407,"total_prev_val":728951596},{"prev_address":"37mkZ8h5KaGPngQSKDusFZekaNhgLKPqBc","curr_value":1926487,"prev_time":1546146587,"total_prev_val":765592361},{"prev_address":"3M2nrHRijWYhkTuxv8rrG1ftFi3sTFNNd2","curr_value":1127803,"prev_time":1546156201,"total_prev_val":509474556},{"prev_address":"3938rcFyytX4mh7Lugm7Guaxdjwx6bobJ8","curr_value":1150000,"prev_time":1546112915,"total_prev_val":5249377480},{"prev_address":"3H43MPu6XgbFhNSRVuEzsYgGWNSufPPpoH","curr_value":641360,"prev_time":1546184226,"total_prev_val":3766100577},{"prev_address":"3Q4rMLM6jbEC7Z3NxMUswKQN3FKunKg6WU","curr_value":1422603,"prev_time":1546167783,"total_prev_val":537419704},{"prev_address":"35qDo3rJoeG3r17iUJ5PcHQqTLPkpMHmWk","curr_value":1465417,"prev_time":1546119150,"total_prev_val":1371788679},{"prev_address":"3BfoVtJkTCNn23B6HEAUpMkupoo9RTPoBQ","curr_value":1963662,"prev_time":1546180824,"total_prev_val":815169059},{"prev_address":"3JH15PWvg4ie8HkgXqr1JCfq4qZYQxMkbr","curr_value":566777,"prev_time":1546184226,"total_prev_val":6015900910},{"prev_address":"32Rz1Dn872u7Lt6PcRa94RLuzFeJzWhq5a","curr_value":1428440,"prev_time":1546124162,"total_prev_val":1558865576},{"prev_address":"3JoEa19vMbzD69CfvbcyUzPUraMk48fzkC","curr_value":522273,"prev_time":1546174356,"total_prev_val":46910669},{"prev_address":"35Be8T5U3jG15AGqLzaTcS6n8T7nvLvts5","curr_value":2797038,"prev_time":1546165361,"total_prev_val":1150118309},{"prev_address":"379rEToRuRz9B6Hjwhp5XQGKpgTXEQroqM","curr_value":2323823,"prev_time":1546030525,"total_prev_val":1582752121},{"prev_address":"3BWSRQYWyKQkjRVv3KRJnVDUoQ2Yq69ko9","curr_value":2047793,"prev_time":1546168619,"total_prev_val":2738622},{"prev_address":"3Jm5Wpbhdce5YaLCuqAUnpudkRmHCTiBf4","curr_value":2892619,"prev_time":1546174866,"total_prev_val":182046012},{"prev_address":"3FvMRhqrMx9247Nor9KsSzcqz94trHcGym","curr_value":1751070,"prev_time":1546179553,"total_prev_val":2758639},{"prev_address":"3JYaikB1JdixEEJrz3KwpwrMZknfKx3UUc","curr_value":1499439,"prev_time":1546141017,"total_prev_val":928937758},{"prev_address":"3C7ouiu1r4C4iaSzaDQkqV2sEciyn6aCkH","curr_value":1817157,"prev_time":1546146587,"total_prev_val":2055908047},{"prev_address":"35etx6DwNe3cK1kVaNvAZCSkiCMLFbNwmS","curr_value":2107676,"prev_time":1546108943,"total_prev_val":8116638131},{"prev_address":"3JzkH45eRPbEhHXaEiuqJBVQUWCT48qMd5","curr_value":477021,"prev_time":1546165621,"total_prev_val":45775262},{"prev_address":"38C9b1VreRNZMRoA6RmhtM44RJeXb9B6dZ","curr_value":1266781,"prev_time":1546178052,"total_prev_val":5413806688},{"prev_address":"3LjoHYWhP4xkrSABtnQ5MpAYB4vp315RUc","curr_value":1681959,"prev_time":1546175452,"total_prev_val":38877363},{"prev_address":"3DrwCkgB9VDLPkzNz2BZn1svG6abzRwvrR","curr_value":571602,"prev_time":1546178052,"total_prev_val":109773675},{"prev_address":"3Px7QeYsswrXLZXZyxvaq9vRj1daSbJCbo","curr_value":1259451,"prev_time":1546107426,"total_prev_val":5036613092},{"prev_address":"3JK3varvMwo2jdQC5XWxFubyeKLenb1iXN","curr_value":539063,"prev_time":1546172918,"total_prev_val":2658799922},{"prev_address":"35spRXWvvtpGr4S3jUYQoKWXRertPSpbqJ","curr_value":2469512,"prev_time":1546127082,"total_prev_val":10045979},{"prev_address":"3H2dSFKw6G9bKduPG2MaBogk8xposSogF6","curr_value":402194,"prev_time":1546098523,"total_prev_val":123614927},{"prev_address":"3PW7rQTq5KAodJrnXwYenxbCvj71iiKRsg","curr_value":2857256,"prev_time":1546032024,"total_prev_val":27143610},{"prev_address":"39yoABsyxMSP1AtZZYJg5ZTbSdgZqU37KC","curr_value":1962930,"prev_time":1546174356,"total_prev_val":500659771},{"prev_address":"3LcTrw6Lys8DvhYAuzbvMUGNc75xSZDnKG","curr_value":2132050,"prev_time":1546021121,"total_prev_val":3764701813},{"prev_address":"398YLrRnkr6o1jM9tZCi2vvPEkQpxEi9Ue","curr_value":1563396,"prev_time":1546182093,"total_prev_val":12810487},{"prev_address":"39n8T8YsiZRWHpNm9u3jwz6844hWE4Q81U","curr_value":1887000,"prev_time":1546084370,"total_prev_val":377048490},{"prev_address":"3BeXELMoMkrHN9mWGCN7F3maASRoFnYC8t","curr_value":516018,"prev_time":1546178864,"total_prev_val":4538000309},{"prev_address":"3D4h4Jat6sGjmZLiqFgk3QDmQMn99EmKP1","curr_value":3048161,"prev_time":1546088367,"total_prev_val":791071960},{"prev_address":"3Ay8DTVTgQ5U3pjmNfdLcZusDRpT8rndoq","curr_value":1806601,"prev_time":1546108943,"total_prev_val":4266994768},{"prev_address":"38ZLqsitRfA4ztXbzUnMk5HvYzyNaxCVqA","curr_value":2497510,"prev_time":1546104393,"total_prev_val":387625915},{"prev_address":"3HaeAMsELWGNf9a33FKTut94fErgy35Ug2","curr_value":1340397,"prev_time":1546172918,"total_prev_val":1859973428},{"prev_address":"32CcdsApRRNDSKTk2tpJvVLihukpBKDvmM","curr_value":1590000,"prev_time":1546162895,"total_prev_val":1919150181},{"prev_address":"35vJBcecPNkzuCEE7rJDZb7vkFQHcxY7TK","curr_value":460950,"prev_time":1546174356,"total_prev_val":716898911},{"prev_address":"3NRPWDbfBxH7FyEfEr2HgqHo6He59N2Mb4","curr_value":2901000,"prev_time":1546170730,"total_prev_val":9290000},{"prev_address":"3PHn5zZuJaXujjexjPvAmFZQp725qHL4SQ","curr_value":1435658,"prev_time":1546171366,"total_prev_val":17807139},{"prev_address":"3M68v9ym4dLsNsytvALA8XskDmgb7u93YB","curr_value":1118201,"prev_time":1546121810,"total_prev_val":568170990},{"prev_address":"3Q17fsnpWLV8wu43ZvxJCnZa678sgbNbKW","curr_value":2330190,"prev_time":1546096389,"total_prev_val":927902449},{"prev_address":"33WkY9Dqo5MCa1W6cEkatarhsGzMmUwPw5","curr_value":1238000,"prev_time":1546169712,"total_prev_val":332594836},{"prev_address":"37JZD6YraSeuZYANGqvniHoWC9wdKn7wp2","curr_value":2880000,"prev_time":1546071618,"total_prev_val":17378637},{"prev_address":"3CZhKHyCg3Ez3d5KybQnuxgkciGFfuvU56","curr_value":427780,"prev_time":1546184226,"total_prev_val":3433412774},{"prev_address":"33ZWsTn8MY5hugytEtwGK3upzfAxR4FPGB","curr_value":1262657,"prev_time":1546161936,"total_prev_val":1568251280},{"prev_address":"3KWcTMb4R9ZrEi7thcj4Cnj8xWjGpynyAr","curr_value":1255135,"prev_time":1546110937,"total_prev_val":479382086},{"prev_address":"36mbP1f5h4Y1Aj3ductg4PUZZ5q2ProRh1","curr_value":1304605,"prev_time":1546174370,"total_prev_val":1447953676},{"prev_address":"3EmwmUouafrULRrqQz6j7jVMQFnFbDRrY7","curr_value":1154688,"prev_time":1546172918,"total_prev_val":86307381},{"prev_address":"33kYhPLvcRoGDNBBdPap94AthuhgS15Dtn","curr_value":1351688,"prev_time":1546061256,"total_prev_val":883556318},{"prev_address":"3BJfQZuq76qX4q9rXPQ3Fv74XKXHLw6CWx","curr_value":1433602,"prev_time":1546090252,"total_prev_val":2078503763},{"prev_address":"3M47FVdfoc5QDUGopHmxBDSiHJTD3Ho8fw","curr_value":691864,"prev_time":1546178864,"total_prev_val":998940446},{"prev_address":"3PsB4B6vwPQqUVVPyKjfzBU7DrKy1tmvsQ","curr_value":1862145,"prev_time":1546167385,"total_prev_val":6953967500},{"prev_address":"38rJTqqP2w6RKPdmNAYBKHwbQRBDF2yYHE","curr_value":1337697,"prev_time":1546146587,"total_prev_val":9918597},{"prev_address":"3NfziBHQeDtjcP5itYb3YhDukNSZbuQoBz","curr_value":3259937,"prev_time":1546098523,"total_prev_val":5157916706},{"prev_address":"3HQhKRGfz5oubMFw888xpb5LNJAgCrDk5k","curr_value":644351,"prev_time":1546184226,"total_prev_val":437648021},{"prev_address":"3H44tBfZf4fgRjfKeJX8wRYwC6RWvcCxWN","curr_value":1410540,"prev_time":1546168619,"total_prev_val":3900000}],"max_next_time":1547051598,"min_next_time":1547051598,"avg_next_time":1547051598,"max_next_val":8379978315,"min_next_val":8379978315,"avg_next_val":8379978315,"list_of_output":[{"next_address":"3LVkXjjqxyLPU2WQdMY7Zyi9i4GVsPNJMz","curr_value":152752186,"next_time":1547051598,"total_next_val":8379978315}],"diff_max_prev_time":1419,"diff_min_prev_time":282892,"diff_avg_prev_time":48302,"diff_max_next_time":865953,"diff_min_next_time":865953,"diff_avg_next_time":865953}