{"txid":"cc2725244216efc3d0db6a57d4d7db3c4ebcda3650ef90b27f4573531bea52cd","confirmations":3650,"time":1557258340,"is_coinbase":false,"is_double_spend":false,"is_sw_tx":true,"weight":19515,"vsize":4879,"inputs_count":50,"outputs_count":10,"inputs_value":123790898,"outputs_value":123433126,"max_prev_time":1557255573,"min_prev_time":1556918411,"avg_prev_time":1557248830,"max_prev_val":5574386991,"min_prev_val":4696939,"avg_prev_val":1448104712,"list_of_input":[{"prev_address":"3BPfXVQpxuQM1BjfvdXQtBZbxDSF7Jr7Gf","curr_value":19838,"prev_time":1557255573,"total_prev_val":1787958267},{"prev_address":"3C4RtwWMEXhBomPWTFbwoLTVDYhJu3mU84","curr_value":88675,"prev_time":1557255573,"total_prev_val":221315685},{"prev_address":"37fxhBa8Vmc2VPpze6fB2wsed9ZYLy8cLU","curr_value":50002,"prev_time":1557255573,"total_prev_val":1585384231},{"prev_address":"39cvjGr35Qq3nzapwfiioJQWXerDLCSGsE","curr_value":14800,"prev_time":1557255573,"total_prev_val":5116542},{"prev_address":"38ASdWKErq6NtCt3753wThMSjHosMGwVKu","curr_value":201938,"prev_time":1557255573,"total_prev_val":5574386991},{"prev_address":"36zuK8SfFasudcS9UPXYwDUFowEKSL2JcA","curr_value":183679,"prev_time":1557255573,"total_prev_val":2207811771},{"prev_address":"3LiJEtDDzhXkxdMpLLpNMebh5GzXNQy87j","curr_value":229621,"prev_time":1557255573,"total_prev_val":2451926572},{"prev_address":"38q2xgihRqpWCVRnr32Q7WWXBuzFdikXCx","curr_value":235887,"prev_time":1557255573,"total_prev_val":1585384231},{"prev_address":"3F76jKWeiJv3iXJjukENM7sJR4z5u9s9jM","curr_value":243212,"prev_time":1557255573,"total_prev_val":307862541},{"prev_address":"3Qx2tnw2sTaECoWqKZX6f5Gab7SSG5JeBX","curr_value":50903,"prev_time":1557255573,"total_prev_val":2461621235},{"prev_address":"39LKSdJbncz4XAeHE1fSo3mdayubDwUxgu","curr_value":184490,"prev_time":1557255573,"total_prev_val":2409766720},{"prev_address":"3FWmtpMLjq5M92CeB6yZkQVHyDxwS7ZE9e","curr_value":178523,"prev_time":1557255573,"total_prev_val":307862541},{"prev_address":"35RYJT6Me2nahabH9cxd1c4jVknCHeoT2T","curr_value":206192,"prev_time":1557255573,"total_prev_val":1628283108},{"prev_address":"3Gk6wLbkV9VN9ZJq5joJaE27iWiHFFV7ar","curr_value":120481,"prev_time":1557255573,"total_prev_val":5069736},{"prev_address":"3AhkQRBMhuXqK9sMjr62MsnRfruUvciLe1","curr_value":205393,"prev_time":1557255573,"total_prev_val":1628283108},{"prev_address":"37hj1KLGhEE3jcpoW6incdzDVvPvLSrWtC","curr_value":160302,"prev_time":1557255573,"total_prev_val":21912504},{"prev_address":"3PKEwpMNMCe4cjhbrUesD8ZAbEHB2pziuL","curr_value":139161,"prev_time":1557255573,"total_prev_val":221315685},{"prev_address":"36ZT8Y8UtWj1qkSpdKfRbwY9Bu4fQqJb76","curr_value":37500,"prev_time":1557255573,"total_prev_val":3068910616},{"prev_address":"3JAbeiD2gbfRiamQUCrokjmjRkYrxDCK2P","curr_value":20119,"prev_time":1557255573,"total_prev_val":307862541},{"prev_address":"32Wv4HRxZHwZ2gcSs12Wo2xkdfV4fm8ULQ","curr_value":181286,"prev_time":1557255573,"total_prev_val":123198851},{"prev_address":"37E3LZYfzJAQUYer55g6MVkv3HFgmgeCge","curr_value":58843,"prev_time":1557255573,"total_prev_val":223153104},{"prev_address":"35irsLaMFSRxrJriwKnftoUyWy8Qhp69sF","curr_value":52418,"prev_time":1557255573,"total_prev_val":221315685},{"prev_address":"3Jh3P1J84v8eL5kyqFgYkhrT1pDp2nD27U","curr_value":233874,"prev_time":1557255573,"total_prev_val":1158088481},{"prev_address":"34vrqehYV6kW3KLDGTdHsk7qU1JBRRnrgr","curr_value":94404,"prev_time":1557255573,"total_prev_val":495601056},{"prev_address":"38MDKa4aLwhDzgFZCvH6oMe5AzMSWUzU8K","curr_value":224265,"prev_time":1557255573,"total_prev_val":8868375},{"prev_address":"38Q9AgvcMfMqKuAzjwEZyJSVEWibmgz9mR","curr_value":241024,"prev_time":1557255573,"total_prev_val":5574386991},{"prev_address":"37SQPfUC8tztab8b9ZW2DwwaQt7R1V9ejr","curr_value":213785,"prev_time":1557255573,"total_prev_val":2409766720},{"prev_address":"3Hxh7C8W1a9e8wk9WzKQBq6MYFTr6i5gVV","curr_value":81892,"prev_time":1557255573,"total_prev_val":1158088481},{"prev_address":"39pSvPoA71f1aFgScazs39LgF4vt3BGemP","curr_value":229171,"prev_time":1557255573,"total_prev_val":4937954},{"prev_address":"34eRAdfa6R6FVtcaWgGwZD9Pt6dBqR7R8d","curr_value":20119,"prev_time":1557255573,"total_prev_val":1787958267},{"prev_address":"3PczrVC5GxzM8JLN68GYUp1f7T7WQKYC2s","curr_value":186146,"prev_time":1557255573,"total_prev_val":2461621235},{"prev_address":"3Bkvzqj7yTS19zKCqg8uiFpmYHK6LRtjP9","curr_value":120775,"prev_time":1557255573,"total_prev_val":4696939},{"prev_address":"335pCykbZ5A5JKYNSSkbLx1Ygh75VJU1V3","curr_value":243211,"prev_time":1557255573,"total_prev_val":1628283108},{"prev_address":"34Tmi4FPnbUXTkSC1sjXJXZFKKCpAdHFEc","curr_value":76198,"prev_time":1557255573,"total_prev_val":2099388857},{"prev_address":"3CQs6MPyBPhydxa5vFDJmE4iuBah3KDhy6","curr_value":10000,"prev_time":1557255573,"total_prev_val":3068910616},{"prev_address":"328daFehfCvBacCoWXLUifcMvZNh76PPrD","curr_value":197788,"prev_time":1557255573,"total_prev_val":1628283108},{"prev_address":"31jDGeQ7HiHdmLniGsV8r42f8HfUDqqSGv","curr_value":12948,"prev_time":1557255573,"total_prev_val":221315685},{"prev_address":"3Mybs2836ck7JeRJbmhFHGhSnThorxwZGh","curr_value":134417,"prev_time":1557255573,"total_prev_val":2207811771},{"prev_address":"33dEngDHjvsnfLuaHrNqYrGfeEgwa3m8k3","curr_value":117259857,"prev_time":1556918411,"total_prev_val":117456073},{"prev_address":"3Fthtd3tunW5Nkkfi5RButFsTGuJvMhb8j","curr_value":195253,"prev_time":1557255573,"total_prev_val":2207811771},{"prev_address":"3GKo94MUMoYhgEQrbHYT1bcSFvfLU2QCYs","curr_value":121326,"prev_time":1557255573,"total_prev_val":1585384231},{"prev_address":"3EnSN1dkC1fvoFwy4UNaA95pradCNs8Awh","curr_value":121904,"prev_time":1557255573,"total_prev_val":2461621235},{"prev_address":"3MmPDqDd6h5CK1EKyFSc115Jf8ghgsoMsV","curr_value":12000,"prev_time":1557255573,"total_prev_val":1585384231},{"prev_address":"3HRkmAJuQqV9oVdJhKcVUESgmL2imbdZDx","curr_value":32678,"prev_time":1557255573,"total_prev_val":2461621235},{"prev_address":"39qB79FsnBgNpDwLhkGMq9GG3gvUrMHq2j","curr_value":18942,"prev_time":1557255573,"total_prev_val":1787958267},{"prev_address":"3CGKW8KaM1Cgrh5FHPPaTqJw54qXY2gWLt","curr_value":235811,"prev_time":1557255573,"total_prev_val":2541380690},{"prev_address":"3HUEB6v4LQeh3C5FuYt4q4BXdugkWABVsw","curr_value":231714,"prev_time":1557255573,"total_prev_val":8503862},{"prev_address":"3NLu9gUfj4hruwnPgXRuJFqMy3VCNK1ywg","curr_value":10000,"prev_time":1557255573,"total_prev_val":1158088481},{"prev_address":"3AL1wg17gYrJwT88FAhnqUZJvqGkeJ328M","curr_value":230276,"prev_time":1557255573,"total_prev_val":8503862},{"prev_address":"3CrC7fffzYX3iDo4rW1tchLSxmRdd8pM9a","curr_value":137857,"prev_time":1557255573,"total_prev_val":2207811771}],"max_next_time":1557996512,"min_next_time":1557262410,"avg_next_time":1557358225,"max_next_val":3136729176,"min_next_val":400000,"avg_next_val":1110674413,"list_of_output":[{"next_address":"38c9q8DRg8RCzBhGEFQZw7r7aXmVtt38Kf","curr_value":8327932,"next_time":1557264684,"total_next_val":2994920143},{"next_address":"3JZPVckpgbFamKoejeeoSwZTWPMeXKFjSw","curr_value":5147704,"next_time":1557293675,"total_next_val":23643806},{"next_address":"1FFgF66FHgUW1b8pdXwob5N6rVyVHXdHua","curr_value":45327852,"next_time":1557264684,"total_next_val":45327852},{"next_address":"3Q4DzVcWXsJMMTJW3A5UhaTbgc1SLHtbMr","curr_value":1400000,"next_time":1557264684,"total_next_val":2994920143},{"next_address":"1R4VV31p6989ubdkoTNexKiVYd7AAP8bH","curr_value":39954528,"next_time":1557262810,"total_next_val":39954528},{"next_address":"3MSeo5LwgBafzvwftBfVaNEd7yfRzbfG51","curr_value":4306286,"next_time":1557443685,"total_next_val":395074076},{"next_address":"3KjAHLNwyHWyx1QSCKAGiDnwnYY57LwkwR","curr_value":1302552,"next_time":1557264421,"total_next_val":3136729176},{"next_address":"3GH1cyv7rwsVythwSH4J8V8L6tHnCznTMi","curr_value":800000,"next_time":1557262410,"total_next_val":856109089},{"next_address":"3FhPkjopV8T2WdfVUBUpVgAARqNimANYZ7","curr_value":400000,"next_time":1557264684,"total_next_val":400000},{"next_address":"3MRvjUGfocNCNtBrq4idqzWjHgodUVCvnw","curr_value":16466272,"next_time":1557996512,"total_next_val":619665317}],"diff_max_prev_time":2767,"diff_min_prev_time":339929,"diff_avg_prev_time":9510,"diff_max_next_time":738172,"diff_min_next_time":4070,"diff_avg_next_time":99885}