{"txid":"cf2ea3ea810c650cf981f0696184922b8d2f8f1bdce5c704921d16e5d8729bff","confirmations":24418,"time":1545059448,"is_coinbase":false,"is_double_spend":false,"is_sw_tx":true,"weight":77455,"vsize":19364,"inputs_count":209,"outputs_count":11,"inputs_value":1051928102,"outputs_value":1051637042,"max_prev_time":1545057801,"min_prev_time":1539171859,"avg_prev_time":1544695426,"max_prev_val":5661946917,"min_prev_val":216670,"avg_prev_val":1401043120,"list_of_input":[{"prev_address":"3GwACMnVv1p8AZyVoYbjGRXWgjHmYVQS8H","curr_value":389116,"prev_time":1545057801,"total_prev_val":6355745},{"prev_address":"3GyvyPxND81WEp8W7gDAn21kDhTRdDf2x6","curr_value":13697882,"prev_time":1545047634,"total_prev_val":98799231},{"prev_address":"3HMg5EA1ntjPsSwn5w86hwFpohM2zEwn8f","curr_value":13044209,"prev_time":1544924663,"total_prev_val":1593617185},{"prev_address":"3Qxt6XWE2i8DNutfhpZUr49E3fMNfLK6mN","curr_value":542800,"prev_time":1545057801,"total_prev_val":5297487733},{"prev_address":"3Jyb41bJ4ch6SjohM15MUQNtMku9G6rVxb","curr_value":565066,"prev_time":1545057801,"total_prev_val":5297487733},{"prev_address":"3LwzeNYkXjLMtwerNRzd653qYQLksS2uks","curr_value":287979,"prev_time":1545057801,"total_prev_val":796932969},{"prev_address":"3Msz89PWarB76nBTzzY4Te88TmfK2YmP8p","curr_value":1099837,"prev_time":1545057801,"total_prev_val":21763895},{"prev_address":"34ahtMV3TY1bhFmWSrtn3rSsEacvjA2yZk","curr_value":1003416,"prev_time":1545057801,"total_prev_val":5297487733},{"prev_address":"34tWwBbpp17JrVbU4iu7Rxb3eEUiR16NSP","curr_value":835407,"prev_time":1545057801,"total_prev_val":5297487733},{"prev_address":"3FemqfJMVhWmRuLnrVJswebxFfnkvuFgBg","curr_value":443980,"prev_time":1545057801,"total_prev_val":1032613661},{"prev_address":"3Ac2jqJ9QX2fpQuksdzo5RddLPADdi5FZy","curr_value":484859,"prev_time":1545057801,"total_prev_val":796932969},{"prev_address":"3PBe4qjtL8J238MgSG9PvxUtAJJUF6yHmk","curr_value":287888,"prev_time":1545057801,"total_prev_val":5297487733},{"prev_address":"3PSwm9Sqjyqw7cyWsiPFtNpUXxMUeJx3xA","curr_value":420429,"prev_time":1545057801,"total_prev_val":796932969},{"prev_address":"3BXSX6GfqesdouJjpTnHcsr8UsnBXknWUD","curr_value":323810,"prev_time":1545057801,"total_prev_val":17110537},{"prev_address":"32M5Xbo2zSj7JJYGvjiqcfPeeTqz4rTmMA","curr_value":14239395,"prev_time":1545045216,"total_prev_val":1134409682},{"prev_address":"3FkvSK9vG9rJxo2hWtyKFhDahuwPGA3MaT","curr_value":12151958,"prev_time":1545050542,"total_prev_val":2425937681},{"prev_address":"32ukAUeBxQTWxpY9JLHSgsiWFZNPGrJKTS","curr_value":500689,"prev_time":1545057801,"total_prev_val":1032613661},{"prev_address":"3GJdPQNy3A6mC8sWnpjuFar6ceNQMw2YdL","curr_value":11545422,"prev_time":1544907122,"total_prev_val":2700432222},{"prev_address":"37tZu23HdBA9xkYQJcKegSwv6B6j15aimy","curr_value":192582,"prev_time":1545057801,"total_prev_val":796932969},{"prev_address":"348d8Q9zGnVmQeKC3tk8xZCKZ9zvsBUr5o","curr_value":749085,"prev_time":1545057801,"total_prev_val":96192969},{"prev_address":"3LoSfUsBnUQ4GruLqPstXvawRNYYWV4WqY","curr_value":11546100,"prev_time":1543065222,"total_prev_val":758580527},{"prev_address":"3MuysKMmiWmnp2twgKSCPninJwXKE3F4YE","curr_value":823135,"prev_time":1545057801,"total_prev_val":796932969},{"prev_address":"3NMSdAwmcpTMyn3Wk1K72imF3ttuA1e3uK","curr_value":13918284,"prev_time":1545057036,"total_prev_val":1886484034},{"prev_address":"3Db2Rd62kvrrX5XVWsF9CCqt2z7Lfr149j","curr_value":645936,"prev_time":1545057801,"total_prev_val":1032613661},{"prev_address":"3LuM5SgBWRrJFHt6nvHH8hfzJv8VtrxoPd","curr_value":492781,"prev_time":1545057801,"total_prev_val":15000000},{"prev_address":"38wJENU82RW56fEVeHwxkrLrbXBCGYZa77","curr_value":15194,"prev_time":1545057801,"total_prev_val":5297487733},{"prev_address":"3K5Vr35MwypuW1uskzEWC5CXt5y2eJYy1H","curr_value":411687,"prev_time":1545057801,"total_prev_val":647771},{"prev_address":"3LDHuDCFMQq5yzYoELun877zFp1r1hhpmR","curr_value":543305,"prev_time":1545057801,"total_prev_val":96192969},{"prev_address":"3G1AGbnga4L5QTuW9HSvtF8v4CZVzqPbU6","curr_value":641333,"prev_time":1545057801,"total_prev_val":5000000},{"prev_address":"3KFJGabdWvn53PrSz2Cu1GdnFEkwFtzGQX","curr_value":11547500,"prev_time":1541372118,"total_prev_val":2203695701},{"prev_address":"3MMFxYidygBHukoU6PYFB7af7aZDgm9hbe","curr_value":934181,"prev_time":1545057801,"total_prev_val":796932969},{"prev_address":"3JmQ1CaREtiGfPw5epNGmyzA32ma1YBx4M","curr_value":627441,"prev_time":1545057801,"total_prev_val":796932969},{"prev_address":"38JhQeS2pNMrBoub2PxhJwFgJ7N7fYpiUA","curr_value":412858,"prev_time":1545057801,"total_prev_val":6118979},{"prev_address":"3B3L9sJts87bGdD27tkWLXrZ7eCH8mYk5c","curr_value":12030011,"prev_time":1545053562,"total_prev_val":4188322159},{"prev_address":"3JskTMRaYi2SzVxjsUK4H7uphkCipa8mof","curr_value":809023,"prev_time":1545057801,"total_prev_val":1032613661},{"prev_address":"3JfYoTdRrR7jQ3RXwzkwUxptTvQN2taG5M","curr_value":11539000,"prev_time":1542265697,"total_prev_val":59533500},{"prev_address":"3MR4ENXxufeHMpWg3AxYBazMaEtCxG28DZ","curr_value":11533884,"prev_time":1543245735,"total_prev_val":1535331615},{"prev_address":"3GZQTnW56Pz9c7ZPyizEKnnBs2oxVRxmwy","curr_value":12380000,"prev_time":1545053562,"total_prev_val":1296144631},{"prev_address":"3HUGgaTGYBSBPf1bDimAQpfAvePQfm3D8A","curr_value":1000553,"prev_time":1545051300,"total_prev_val":3677359},{"prev_address":"3EppFbMVBfn3LVy1kZ5M7Uc6EtXrxxXsDS","curr_value":12772376,"prev_time":1545053562,"total_prev_val":418281793},{"prev_address":"3HsAA75qwiqJpxGJ66T2NEN7p31b8dtoGp","curr_value":208467,"prev_time":1545057801,"total_prev_val":216670},{"prev_address":"32PKczEEkHrj3BT24T4K5vt9H9c8CEae6g","curr_value":11538943,"prev_time":1544373473,"total_prev_val":1104817918},{"prev_address":"3EvefGG5DEARDFdmgeCyoicaWWGgWfPyUb","curr_value":829932,"prev_time":1545057801,"total_prev_val":951164976},{"prev_address":"3NbxrM8jkBeqzrjcRHXVCFnP8qgYJXc97y","curr_value":919447,"prev_time":1545057801,"total_prev_val":1032613661},{"prev_address":"3QEpzEPyguvDVrX8r7AzSP5dQ7GmREWssG","curr_value":14016000,"prev_time":1545037156,"total_prev_val":86599000},{"prev_address":"3AYifhUDgm54GvP9NbxakPjVJ5QoZ4JLd8","curr_value":625252,"prev_time":1545057801,"total_prev_val":5297487733},{"prev_address":"3DMNzCQkwoj6Xs5PwtuqDGXzEMieEQEp7x","curr_value":539617,"prev_time":1545057801,"total_prev_val":1032613661},{"prev_address":"3Bz4dYcsMyE6VXDf1h9CWQfkpcqjmDbD4x","curr_value":542418,"prev_time":1545057801,"total_prev_val":5297487733},{"prev_address":"3PeoGRDY9aPeDY9RdGCJhfCoAKauze5AFK","curr_value":442116,"prev_time":1545057801,"total_prev_val":96192969},{"prev_address":"3JBDCq3FELAsf2Sc3FktDLmn7W9eCtoZ6n","curr_value":748170,"prev_time":1545057801,"total_prev_val":796932969},{"prev_address":"3LzpDiiYrtpHVeZfcRgJBEvfL51Y1wMRhE","curr_value":13036556,"prev_time":1544909412,"total_prev_val":3456360533},{"prev_address":"3GpHNRRAntn8Dx5ZWGpKBSXwpyxP6HtGuB","curr_value":14205637,"prev_time":1545056012,"total_prev_val":3263057547},{"prev_address":"3GotrJ4PJznvL7YkVrLSdPZ83HjaMYVct6","curr_value":11542494,"prev_time":1540242419,"total_prev_val":13595131},{"prev_address":"3FuG6kdsaP3tq98SD3YMGzAHnmQZvwQAcb","curr_value":1003827,"prev_time":1545057801,"total_prev_val":1032613661},{"prev_address":"324knaF9HwdaN2mayv5pSZ67HjeA2faCNB","curr_value":11533462,"prev_time":1544964840,"total_prev_val":1937861935},{"prev_address":"38Wg2mESdvTbcnKych32kCWZ7bx5BzQaK9","curr_value":608727,"prev_time":1545057801,"total_prev_val":20661586},{"prev_address":"3MFkkq82jNbguHAXKtbFL66hB78yinxUAy","curr_value":509708,"prev_time":1545057801,"total_prev_val":10236056},{"prev_address":"38rHpDMiAnwcM5qp41YVfs19T26VMWbFSg","curr_value":811679,"prev_time":1545057801,"total_prev_val":796932969},{"prev_address":"39nwA3DRxw2MrqMGLEo8AcW81yrEF5YtoY","curr_value":236510,"prev_time":1545057801,"total_prev_val":17110537},{"prev_address":"34K8Mi7oxQ4kxHksiEX5ixrzKhp1dpYnwp","curr_value":627658,"prev_time":1545057801,"total_prev_val":5297487733},{"prev_address":"3BVFA6ycQE9PVywSYpuQZge2hvmeoNJeR8","curr_value":668472,"prev_time":1545057801,"total_prev_val":796932969},{"prev_address":"3DTHVhjMghUoN3fbB96PrtKJXeNwq1WkqK","curr_value":796239,"prev_time":1545057801,"total_prev_val":813712},{"prev_address":"3JxGcgVbodCixpM6eDV9LyECU1Ho48eJkm","curr_value":11539588,"prev_time":1542139012,"total_prev_val":1240956826},{"prev_address":"3BUSTH2Goeb6b2Nbhf1zpbhuChWXHZE6pZ","curr_value":11547139,"prev_time":1544282318,"total_prev_val":11605690},{"prev_address":"3AB5P4GFFZxo99jYz7A2Avkq9n4MVYjMLg","curr_value":479619,"prev_time":1545057801,"total_prev_val":796932969},{"prev_address":"32KqvJEji1APVBFciZcg1V25jpwp3zpqfR","curr_value":329729,"prev_time":1545057801,"total_prev_val":1032613661},{"prev_address":"37dfVYYLCmGhHvfsVQPgox1YVPfzvGhoRN","curr_value":667269,"prev_time":1545057801,"total_prev_val":5297487733},{"prev_address":"3QXVYRSeXGgM3GYhz5h3ASnmu3JMxypEmk","curr_value":958553,"prev_time":1545057801,"total_prev_val":96192969},{"prev_address":"3GynUVqY5E9TYu2hUKqepT86Wnq88SbavZ","curr_value":394018,"prev_time":1545057801,"total_prev_val":13748159},{"prev_address":"3CJqmSAJc2moJBfEStbdzF7x8JEVE4dFa1","curr_value":627114,"prev_time":1545057801,"total_prev_val":5297487733},{"prev_address":"3KvvfWFFqf1ENw6FdRpqKXJZgFCi7ribJq","curr_value":765333,"prev_time":1545057801,"total_prev_val":5000000},{"prev_address":"3D9KyTbdf6rQGT8nKWF8d8gzPEstVBFAVw","curr_value":520000,"prev_time":1545057801,"total_prev_val":5297487733},{"prev_address":"37Z8bAAyJzrvaL1FAtCwYR553TCxYUf28t","curr_value":525612,"prev_time":1545057801,"total_prev_val":96192969},{"prev_address":"35bojExyCJkXsK3sCHbSDB8TVzjmDsNHF6","curr_value":13037299,"prev_time":1544954503,"total_prev_val":97808159},{"prev_address":"33xzRxzc2N3dcmx3ofCAZhJfzH8h2UdMXF","curr_value":14720000,"prev_time":1545050542,"total_prev_val":3218144440},{"prev_address":"3PmD1KkgdBeqo2GLcxebMA8kjyDcCT4Rqd","curr_value":976810,"prev_time":1545057801,"total_prev_val":17110537},{"prev_address":"345xHvBXKkn7dvzYpjA3oGk4tNJ5QZBXWJ","curr_value":197500,"prev_time":1545057801,"total_prev_val":796932969},{"prev_address":"3ByzL3njBjRiKSogvZd1E4h13SaZpc9UXn","curr_value":14168270,"prev_time":1545057036,"total_prev_val":2227599224},{"prev_address":"3KgzUXeZ1MMJ7jDYzm4MqkPS7Jt6aFVeau","curr_value":455270,"prev_time":1545057801,"total_prev_val":5297487733},{"prev_address":"3Ka5CVcKS25PTJkcqz4c13gnLLtVzbPvc1","curr_value":576316,"prev_time":1545057801,"total_prev_val":578576},{"prev_address":"3F2SiE9NxVy2xCH3Xo2huHgBtPSfanoYZs","curr_value":13890400,"prev_time":1545039403,"total_prev_val":212832931},{"prev_address":"39Awq6W7vYG2K8ZXPuznHySLQEtMwnLTJm","curr_value":11539300,"prev_time":1544906240,"total_prev_val":113891136},{"prev_address":"3ErEHDU5aCP42wvWSME52YHCT1V74wDTjx","curr_value":11541429,"prev_time":1539508158,"total_prev_val":5333304992},{"prev_address":"3KPFfVXCUgVvH4VPkxCyGh85nQXZWMFMJD","curr_value":469224,"prev_time":1545057801,"total_prev_val":4555602},{"prev_address":"3F1L4chd1P23jCBVddpxqr2Lpv9EcqxMYx","curr_value":873698,"prev_time":1545057801,"total_prev_val":796932969},{"prev_address":"3AiJSojqjaXncH29uUxoA4ZQ4TT92GPB3U","curr_value":14549989,"prev_time":1545051158,"total_prev_val":1699376116},{"prev_address":"3Ay9WiMPQHzhmVRKZUYfkZycNgSF65gr8V","curr_value":885561,"prev_time":1545057801,"total_prev_val":6118979},{"prev_address":"3LL4qLYZFB8wgoWHJ6qWzyBRsiqUW3wfaF","curr_value":11600000,"prev_time":1545054002,"total_prev_val":25000000},{"prev_address":"3C9veWSJqWvzFT1u7mKURmFtACkbeqRtd3","curr_value":13594237,"prev_time":1545045445,"total_prev_val":60000000},{"prev_address":"377gqwuTwjRYs372BSZkXPuAuEFiqSaEKP","curr_value":877427,"prev_time":1545057801,"total_prev_val":796932969},{"prev_address":"33qdLLrt1wEtuH8tPLdt6PGQUua1cC1FVR","curr_value":585392,"prev_time":1545057801,"total_prev_val":796932969},{"prev_address":"3NFUXgY4pdSvdw9pmJpg5LxeLEJJktDHtt","curr_value":729697,"prev_time":1545057801,"total_prev_val":5297487733},{"prev_address":"3JHQebbtLucGuaMwhCFP3gfyFKLdoVWko6","curr_value":13364782,"prev_time":1545041257,"total_prev_val":131444117},{"prev_address":"3C1xgzFtJ7BDTfRcrFpmP2ZNztsri3mpgp","curr_value":432042,"prev_time":1545057801,"total_prev_val":96192969},{"prev_address":"3QsX1WxmTsUVrX5mfx5Qzx4juQNeN8DRur","curr_value":916424,"prev_time":1545057801,"total_prev_val":968115},{"prev_address":"3CoxvVi44BrSkwVW2MRqhuG8cSxbN4Yvee","curr_value":587095,"prev_time":1545057801,"total_prev_val":796932969},{"prev_address":"341G4kA8Wsw1ngWKhmnBm9Ky5ME95tunGB","curr_value":403163,"prev_time":1545057801,"total_prev_val":5297487733},{"prev_address":"366v3SaQyZ6o2StUm767wbQzzf5mEwCR3Q","curr_value":12300000,"prev_time":1545057036,"total_prev_val":19283139},{"prev_address":"3NQ6z8AyAeCZxZLoNRUmcyQAprMLTKBewu","curr_value":14025330,"prev_time":1545053562,"total_prev_val":4079047193},{"prev_address":"34dQwhGpxnkrNjiwiGbmE9tubdFSXXPH4t","curr_value":11530000,"prev_time":1539171859,"total_prev_val":120444518},{"prev_address":"3QyesKcj2ceGxjee3NSgv2EMdjPL4KzNWy","curr_value":650325,"prev_time":1545057801,"total_prev_val":7018413},{"prev_address":"3BnUPWKf7j5UPAcf6wwXV6z3gEGzFKUa2Z","curr_value":400361,"prev_time":1545057801,"total_prev_val":10597445},{"prev_address":"3Hy9x6o8vz94jvQcp27w9CFFZ3TxmdD3Cd","curr_value":812996,"prev_time":1545057801,"total_prev_val":5297487733},{"prev_address":"31kxejJV7WLWjrMQWZfGAvxNxv1G5xWfu1","curr_value":11528490,"prev_time":1543222028,"total_prev_val":1949961416},{"prev_address":"3Nu2u66hnfNXEJvyp4DGcStq1gdXeXVAqb","curr_value":1066429,"prev_time":1545057801,"total_prev_val":796932969},{"prev_address":"3DQ8xBgmzFAJwtqq9LBKh91pxJ916YFdHE","curr_value":11527597,"prev_time":1542439658,"total_prev_val":481818254},{"prev_address":"33sPjYtFFuBdsfeW5y3Ury2b8VXe8BMEwn","curr_value":476101,"prev_time":1545057801,"total_prev_val":6118979},{"prev_address":"3F7m7mwWqf7SZxdiG6QTw8z5JCAiDLyf3T","curr_value":13100000,"prev_time":1545035808,"total_prev_val":49652600},{"prev_address":"34bqM6FAYo1TH7g2ko1TSFLLuWJCzpG8DL","curr_value":11548442,"prev_time":1541363951,"total_prev_val":1114943166},{"prev_address":"38d2cSzMsn8BvtJbPdXeiCzzE1yTGXcET6","curr_value":14064140,"prev_time":1545056012,"total_prev_val":16519857},{"prev_address":"3A1nsGjhMXSZtAeWTPQJEGYWV41Wx48Kmo","curr_value":198336,"prev_time":1545057801,"total_prev_val":96192969},{"prev_address":"36iJGS4tEJmGzmebd9g99BySD9L4iZnpLN","curr_value":1084690,"prev_time":1545057801,"total_prev_val":796932969},{"prev_address":"3F6s7SFqEeXbK92iDH1HQCoStV4B9tjU8y","curr_value":14659987,"prev_time":1545050691,"total_prev_val":50222146},{"prev_address":"37sY6Crgbbc35ZugZWg5UmZvZVZ6ukLzsN","curr_value":13800000,"prev_time":1545043062,"total_prev_val":2665714196},{"prev_address":"3FdW9SdEeAoeikbSRnaWVs5K8os42p2Y9z","curr_value":430219,"prev_time":1545057801,"total_prev_val":17992781},{"prev_address":"3JUkbAmmcv9Lmhz9aSrQ2pAUfX1K3YbrW5","curr_value":14024000,"prev_time":1545056012,"total_prev_val":171165000},{"prev_address":"3HFUkZbjejUmYaM3TNJGYxVj2ThcsuZKe2","curr_value":720000,"prev_time":1545057801,"total_prev_val":1680525},{"prev_address":"39jdcBXhVje8aqPVYjeuneZjttT7XLnVpi","curr_value":12174208,"prev_time":1545054002,"total_prev_val":1018318241},{"prev_address":"383kbgLPVX4eN8Y8ZnzU8k5UMnSzuAsjzE","curr_value":11545065,"prev_time":1542096898,"total_prev_val":1956969554},{"prev_address":"3L6MgUWiGZAUdUVgJi9DSEJiSF9TwWDAYw","curr_value":11546155,"prev_time":1543487449,"total_prev_val":3836554587},{"prev_address":"32EkzX9zptYC36hsLGsBx7LqMjRP3VGYxS","curr_value":12000000,"prev_time":1545050691,"total_prev_val":3742696269},{"prev_address":"3KJDrWunDVZHVSJGvztVJp5jtFwP4W3kMp","curr_value":13050089,"prev_time":1544952471,"total_prev_val":4625062116},{"prev_address":"3DgYgehRWJAqxeYM9XzHDCKePCbSx9eLkz","curr_value":399858,"prev_time":1545057801,"total_prev_val":18395111},{"prev_address":"34sWiwgEqd2394HW5ygNFYwP44ToohhG6x","curr_value":648064,"prev_time":1545057801,"total_prev_val":796932969},{"prev_address":"3BtVahBXR19oozQXKrybTDvAa56yZD5Zdx","curr_value":544919,"prev_time":1545057801,"total_prev_val":5297487733},{"prev_address":"3MaSzkJAk6XKem7Q29NZDBctRaFbjq7U6n","curr_value":12810001,"prev_time":1545054002,"total_prev_val":1334292844},{"prev_address":"3K9BPRjYRHES41KwE1NfAU9XtCbX1LeYNs","curr_value":14412823,"prev_time":1545057036,"total_prev_val":2227599224},{"prev_address":"3NAHp8xQuPbSb44dWAvnfgmWdEyJzLmSHG","curr_value":443981,"prev_time":1545057801,"total_prev_val":796932969},{"prev_address":"3PAjwqxuhBYraX1rpj9sWaPJTpxCeXwhWr","curr_value":390554,"prev_time":1545057801,"total_prev_val":23000000},{"prev_address":"37gj7cG7KZwHHoo2E77B958kfzsdK2Ky7w","curr_value":648064,"prev_time":1545057801,"total_prev_val":1032613661},{"prev_address":"31oUYJR1FppH6a3xYbbiPiNJRE6iJTDi5T","curr_value":530000,"prev_time":1545057801,"total_prev_val":2815138},{"prev_address":"3At3d7CcefiEqKauWRwUuN5NEXRNZvBEUf","curr_value":407624,"prev_time":1545057801,"total_prev_val":22173991},{"prev_address":"3D4yQhutXzXAngmcs3k1CREw3ug2VuGktV","curr_value":811679,"prev_time":1545057801,"total_prev_val":96192969},{"prev_address":"32cbdiJLvsUC7h8Fx7g9z6QMZt6g4Jmhfg","curr_value":11542620,"prev_time":1540279020,"total_prev_val":1641243081},{"prev_address":"3A7ostRYEf1xL5bqiZTv9gpnKcu2ynP9yc","curr_value":386830,"prev_time":1545057801,"total_prev_val":1032613661},{"prev_address":"3BSXxrGm3kY9Kqb8ihCiZsDfvpzPQHSUji","curr_value":625338,"prev_time":1545057801,"total_prev_val":1032613661},{"prev_address":"328K4QPZ22DGcvfuNXoHZEFjmHrSYf7ErN","curr_value":13035000,"prev_time":1544853648,"total_prev_val":5661946917},{"prev_address":"3CUMFJXhckXaYK2a6viuRg4c2N2hXAir2P","curr_value":371571,"prev_time":1545057801,"total_prev_val":5297487733},{"prev_address":"35Xfk8UvJLqmG7Gf4tJRR4Htr6UwXGFXhv","curr_value":11544846,"prev_time":1541162613,"total_prev_val":559579099},{"prev_address":"35sQRNjL2Qnk1jKAHZFiHLeq2ixchAwXG6","curr_value":422731,"prev_time":1545057801,"total_prev_val":5297487733},{"prev_address":"3GcuBm96mrnAGJ6wwsgABs44HnHDL6qboq","curr_value":475559,"prev_time":1545057801,"total_prev_val":5297487733},{"prev_address":"39Dk1nWpoAQZ2vUBY74QvPEPZUkHhbwEna","curr_value":13058520,"prev_time":1544861369,"total_prev_val":4951132626},{"prev_address":"35gafD3FfKVwfiVqc63hJ4yppXz29U8FJc","curr_value":13051892,"prev_time":1544799748,"total_prev_val":38758631},{"prev_address":"3EYF4VYnMX97ho5j485buFrRVh7EAKkXzx","curr_value":11788000,"prev_time":1545048386,"total_prev_val":22109567},{"prev_address":"33uhu7uLFEZUXqkwVPpg43b32uH1J26FRv","curr_value":11531000,"prev_time":1544648535,"total_prev_val":1015528920},{"prev_address":"3PB1vcovjgeodGAuyv7xLvJgUAtr2hYdu9","curr_value":500000,"prev_time":1545057801,"total_prev_val":509839},{"prev_address":"3PQKTA3mJ1iTPghw5t52MTwXiK2C6VmHUt","curr_value":967884,"prev_time":1545057801,"total_prev_val":6118979},{"prev_address":"3Ds9dYWutVZhsEzWoh6afVPAYfTYahn1Jg","curr_value":11529079,"prev_time":1539879506,"total_prev_val":4829283482},{"prev_address":"34TibFkL5PLtfbjcXLimZhp182PsT6ySGP","curr_value":1019747,"prev_time":1545057801,"total_prev_val":19417330},{"prev_address":"39BqbxAqEYhqYurzTxjXvj831r1jjazjqa","curr_value":856389,"prev_time":1545057801,"total_prev_val":3328817},{"prev_address":"32qpZLnYSv159wvhikG7noFmq4iLf5sWgX","curr_value":13426683,"prev_time":1545056012,"total_prev_val":79289812},{"prev_address":"32Nd9EQL1WmqyDvrq5CHjVoUhuVir2Npe7","curr_value":800000,"prev_time":1545057801,"total_prev_val":23000000},{"prev_address":"3MBhiv2uJXMVFqMcd9UvUvssv7vxKttZK8","curr_value":13049200,"prev_time":1544901305,"total_prev_val":167918603},{"prev_address":"3J5LjMsZw5xYVGGbRfx7c2AoYNFzUYU5Tq","curr_value":11544000,"prev_time":1544541511,"total_prev_val":24892456},{"prev_address":"35NPpnAph2sFNrP4v2UgWrDebCaBqp4zgw","curr_value":13049830,"prev_time":1544841887,"total_prev_val":5655385319},{"prev_address":"3GyhEgMBVSAGVLNnRi2e2EWYKKuqs2kBs9","curr_value":627735,"prev_time":1545057801,"total_prev_val":5297487733},{"prev_address":"3EwfpHjJk9Pf8UJHFuHJjw8CNihBf2M6ge","curr_value":497723,"prev_time":1545057801,"total_prev_val":96192969},{"prev_address":"39HC5bmpTqxHPrga44sVZdYanf5yXmQPMc","curr_value":381495,"prev_time":1545057801,"total_prev_val":1032613661},{"prev_address":"3QWDG7gN4dyj8isgytdopJuHXZ7WC3CKXS","curr_value":120000,"prev_time":1545057801,"total_prev_val":1964702},{"prev_address":"3G41hnYH5TUvN5jpYEXZQieDsPxEgKuP3N","curr_value":521565,"prev_time":1545057801,"total_prev_val":40522959},{"prev_address":"3JCJgXJ9sVk5iT1pQU9XhJG17dmDvTMHia","curr_value":600000,"prev_time":1545057801,"total_prev_val":1673460},{"prev_address":"3Qx6vXa1vHN3fYbB4CJ2STRZrNScZHcuPm","curr_value":11528269,"prev_time":1544131656,"total_prev_val":528927501},{"prev_address":"3JgVPBsvVQnJKFmoVW8SrGUQe6Bap1oVWW","curr_value":403163,"prev_time":1545057801,"total_prev_val":796932969},{"prev_address":"3Hd5JRt3QRHUzYrMwyXZHh5cM9vFPQsb8i","curr_value":304919,"prev_time":1545057801,"total_prev_val":5297487733},{"prev_address":"3JQ9s8kGyS2nk4kRe6aXaxXk4Epu9odkU8","curr_value":11548205,"prev_time":1544605673,"total_prev_val":2415825133},{"prev_address":"3BQEV7eSj3QhyMspjxsPaM41RY5q1y4QB7","curr_value":236284,"prev_time":1545057801,"total_prev_val":3723535},{"prev_address":"3EJKxBRrRV4oFtT3kejCZqT2Wg6EGU8cB6","curr_value":11541720,"prev_time":1543035014,"total_prev_val":48548515},{"prev_address":"3B9MRt1GDHFw4nfq4WP1QtxLEf5qe71TpC","curr_value":811670,"prev_time":1545057801,"total_prev_val":96192969},{"prev_address":"3LN92d8ccu7ZNeqGV7oCWKDesRfHBBy5Gz","curr_value":13043267,"prev_time":1544955591,"total_prev_val":1191181290},{"prev_address":"34V42KoQnjVX9v6asDKVSKwToWyUACGjqv","curr_value":441902,"prev_time":1545057801,"total_prev_val":1246510},{"prev_address":"3KW3zhdjZRKp8ma3KxWja2DL1TUdojP66C","curr_value":528771,"prev_time":1545057801,"total_prev_val":5000000},{"prev_address":"33hAs7vrTCcdFuoPEWHhPc1Vs1eNzD2ZwC","curr_value":484833,"prev_time":1545057801,"total_prev_val":96192969},{"prev_address":"3B5bLKLBNhZTEeHKuAC7PtjfKvFfb7NSpa","curr_value":14001090,"prev_time":1545053562,"total_prev_val":1377415695},{"prev_address":"3PiZDwkybBkwnEdMTVx4wBiDrjzr6Z9VRD","curr_value":14687049,"prev_time":1545057036,"total_prev_val":4211503112},{"prev_address":"3L2en6Tj1Y7XXCnUJS8fFguYwmy5CgchkN","curr_value":13573702,"prev_time":1545050691,"total_prev_val":52643855},{"prev_address":"354aAKNREXtRbBbqrB1Y6ZsrMAvbVL6UGt","curr_value":650517,"prev_time":1545057801,"total_prev_val":96192969},{"prev_address":"31xdXFEGoDQD3hCuQf9f1Lb8Nyd67WEydM","curr_value":11545012,"prev_time":1541687373,"total_prev_val":437505431},{"prev_address":"3M5pY7c3HizVXMejZDxtKvQoD1ZiMTiAyk","curr_value":646040,"prev_time":1545057801,"total_prev_val":1032613661},{"prev_address":"3Bca6p2CNG2JUoibZFdcWprtFpCoRjpRqs","curr_value":11546155,"prev_time":1543074762,"total_prev_val":832981666},{"prev_address":"3NNpY5W1tA1WwawFWqSeRH9X3hMiakWo1w","curr_value":11547000,"prev_time":1541934723,"total_prev_val":499930262},{"prev_address":"3J5QvbwSB2GTx92ysgaJoXLTvH6MEH64Fr","curr_value":13993356,"prev_time":1545048947,"total_prev_val":469476457},{"prev_address":"3AUB879mG8YaEyxUQwyeYBgyDeLtCjEUr9","curr_value":816458,"prev_time":1545057801,"total_prev_val":796932969},{"prev_address":"33VzPsox4654P2tsKm9HcQbemgUUWFyoVx","curr_value":591809,"prev_time":1545057801,"total_prev_val":96192969},{"prev_address":"3BoSgEGvjeZ7hqX49WPwDcbAkfkYtPYGJr","curr_value":627660,"prev_time":1545057801,"total_prev_val":1032613661},{"prev_address":"35JmMWizuDCMu857ZWCyh32H2N2RFQmSmn","curr_value":277716,"prev_time":1545057801,"total_prev_val":5297487733},{"prev_address":"36vpUsnxtgs1upB1JgSmiefMi3NhqwBpsM","curr_value":867455,"prev_time":1545057801,"total_prev_val":22029488},{"prev_address":"32TdTq8JVfPxH8QG3DJoKbchWisUvdsN4N","curr_value":620008,"prev_time":1545057801,"total_prev_val":6182687},{"prev_address":"3M7yycu4WY4XBP5urwryKfjCLK75jrGfCW","curr_value":1041069,"prev_time":1545057801,"total_prev_val":5297487733},{"prev_address":"3LJRRJUzPp99VKkCWH6CLgGHhxYoLGGWLB","curr_value":11545474,"prev_time":1542871198,"total_prev_val":12197911},{"prev_address":"3HUGgaTGYBSBPf1bDimAQpfAvePQfm3D8A","curr_value":1007429,"prev_time":1545051300,"total_prev_val":205819800},{"prev_address":"34N7EmFJRyMhoTvnVKRwF7wc4LbbFnvVBm","curr_value":1019590,"prev_time":1545057801,"total_prev_val":796932969},{"prev_address":"3HMVDq9fGM65NAUfsjap8rmWFR6VQTE21M","curr_value":346366,"prev_time":1545057801,"total_prev_val":19766168},{"prev_address":"3NJJjSSERkrJArXJP7Pb7yGTuB9pnu8Wza","curr_value":190000,"prev_time":1545057801,"total_prev_val":30901970},{"prev_address":"3PQ3sZ2Sxdh2HoQAiUD85iqUawXsvHpqmu","curr_value":422177,"prev_time":1545057801,"total_prev_val":796932969},{"prev_address":"3JcbXbA1BVT9gufKQ9KZ6wJz5P1Fafjagm","curr_value":11628458,"prev_time":1545056012,"total_prev_val":14549390},{"prev_address":"3Jrz6mZnGrSCChPmDhtxuPnLrbTtf6qkA2","curr_value":1087455,"prev_time":1545057801,"total_prev_val":5297487733},{"prev_address":"3NsWHzhh7DE6UNT2fxqJGXw4JzL9bjyLCN","curr_value":349908,"prev_time":1545057801,"total_prev_val":96192969},{"prev_address":"3NYf9S5Su6LJQwnx5fw8J3u6ggvdCVgTwo","curr_value":372954,"prev_time":1545057801,"total_prev_val":1032613661},{"prev_address":"3BRns6nFUCavbJaWsDuDGzuTTRJx3BmYdb","curr_value":14773560,"prev_time":1545047472,"total_prev_val":2429020203},{"prev_address":"36JqGgmVGEsLsRBRN339zvdQuha4eWwSkK","curr_value":1097020,"prev_time":1545057801,"total_prev_val":137028446},{"prev_address":"35PBKeZNpCyC8FYPB1zjZjnBPEXkNjEshq","curr_value":639555,"prev_time":1545057801,"total_prev_val":2598828},{"prev_address":"39XnP6XBtpwjiPS1bEcJGjKwJZupDWsVXb","curr_value":11535293,"prev_time":1544034131,"total_prev_val":35802730},{"prev_address":"36dHa7DyW62EatsvtpwBKACXdEUaP6AeJd","curr_value":803980,"prev_time":1545057801,"total_prev_val":17110537},{"prev_address":"3MWhBLPFAikR2W9rrFQBnXi3bnFjA55Nt4","curr_value":964400,"prev_time":1545057801,"total_prev_val":2839378},{"prev_address":"3QHA1NmWUXU92qWkGiHFUpKfZF1dzAfbxN","curr_value":562227,"prev_time":1545057801,"total_prev_val":1032613661},{"prev_address":"3MwGF8YL3tSanHfQHjZoBUKwB2EyFgjKs3","curr_value":360000,"prev_time":1545057801,"total_prev_val":5736130},{"prev_address":"3EMKcP8uB4Y4mjQhwPPyZjHrUn1KbsqkWA","curr_value":682837,"prev_time":1545057801,"total_prev_val":5297487733},{"prev_address":"3NUpeLKqBGgV97VW7noMG57ufaVfDKekh8","curr_value":401836,"prev_time":1545057801,"total_prev_val":1032613661},{"prev_address":"37hz31M19X6sJfJxwvCLGm511diwzUzsQw","curr_value":13849699,"prev_time":1545053562,"total_prev_val":2066868581}],"max_next_time":1545069694,"min_next_time":1545060283,"avg_next_time":1545062029,"max_next_val":8742940436,"min_next_val":2000000,"avg_next_val":3643881209,"list_of_output":[{"next_address":"18XaHkSufAmkowwcRwKbCttE1URHcGukHc","curr_value":2000000,"next_time":1545060479,"total_next_val":2000000},{"next_address":"1AsigN1MaS7XWkTU1wipn2pwLH5rj5BHFF","curr_value":15000000,"next_time":1545060283,"total_next_val":15197899},{"next_address":"1EpkQ4dWJWyy9JjgRS7ubaykW4Bv7wgLj4","curr_value":1000000000,"next_time":1545063782,"total_next_val":1000000000},{"next_address":"3ACALPZ6fZxD95e8b1YRGTVonN7Ptefn1Z","curr_value":2720000,"next_time":1545060283,"total_next_val":5501317294},{"next_address":"3JTUCoZVt2f84kiTaYgM1cU9ZDdsjpMe2C","curr_value":2851000,"next_time":1545060283,"total_next_val":5501317294},{"next_address":"3EZh6RN7oNGCwb8akukTa4L3qYyFzpxtt2","curr_value":2000000,"next_time":1545069694,"total_next_val":6834394},{"next_address":"33b11fyKPaikphMVs2tBZ7LvHjAgTVpf81","curr_value":800000,"next_time":1545062323,"total_next_val":8742940436},{"next_address":"31tPjUTJnhMuP9N73KEvSdq6Py9JhRHVU7","curr_value":6500000,"next_time":1545060283,"total_next_val":5501317294},{"next_address":"17T8Yk99YMXtHYPyvLZ3zh4WpFK8ei57FP","curr_value":13005515,"next_time":1545060283,"total_next_val":13005515},{"next_address":"37NE1tpRmW2eGaXHWqYfe59fxagHZDkJkb","curr_value":2589523,"next_time":1545060283,"total_next_val":5501317294},{"next_address":"3JVqkigPFLPTm1yKKpRjLKdKAAF9oM3gTR","curr_value":4171004,"next_time":1545064339,"total_next_val":8297445877}],"diff_max_prev_time":1647,"diff_min_prev_time":5887589,"diff_avg_prev_time":364022,"diff_max_next_time":10246,"diff_min_next_time":835,"diff_avg_next_time":2581}